plotlywaterfall/__about__.py
plotlywaterfall/__init__.py
plotlywaterfall/waterfall.py
plotlywaterfall-0.9.3.dist-info/METADATA
plotlywaterfall-0.9.3.dist-info/WHEEL
plotlywaterfall-0.9.3.dist-info/licenses/LICENSE
plotlywaterfall-0.9.3.dist-info/RECORD
