Metadata-Version: 2.1
Name: plotlywaterfall
Version: 0.9.3
Project-URL: Homepage, https://github.com/docdru/plotlywaterfall
Project-URL: Issues, https://github.com/docdru/plotlywaterfall/issues
Author-email: Daniel Rüffer <docdru.plotlywaterfall@gmail.com>
License-Expression: MIT
License-File: LICENSE
Classifier: Development Status :: 4 - Beta
Classifier: Programming Language :: Python
Classifier: Programming Language :: Python :: 3.8
Classifier: Programming Language :: Python :: 3.9
Classifier: Programming Language :: Python :: 3.10
Classifier: Programming Language :: Python :: 3.11
Classifier: Programming Language :: Python :: 3.12
Classifier: Programming Language :: Python :: Implementation :: CPython
Classifier: Programming Language :: Python :: Implementation :: PyPy
Requires-Python: >=3.8
Requires-Dist: pandas
Requires-Dist: plotly
